ddash/__init__.py
ddash/ddash.py
ddash-0.3.0.data/scripts/ddash
ddash-0.3.0.dist-info/METADATA
ddash-0.3.0.dist-info/WHEEL
ddash-0.3.0.dist-info/top_level.txt
ddash-0.3.0.dist-info/RECORD
