Metadata-Version: 2.1
Name: ddash
Version: 0.3.0
Summary: docker and docker-compose cli tool, to specify and automatic apply with current work directory
Home-page: https://github.com/Ron-Chang/ddash.git
Author: Ron Chang
Author-email: ron.hsien.chang@gmail.com
License: MIT
Platform: UNKNOWN
Requires-Python: >=3.6
